whenami/__init__.py
whenami/main.py
whenami/utils/__init__.py
whenami/utils/auth.py
whenami/utils/calendar.py
whenami/utils/config.py
whenami/utils/llm.py
whenami/utils/nlp.py
whenami/utils/time.py
whenami-0.2.1.dist-info/METADATA
whenami-0.2.1.dist-info/WHEEL
whenami-0.2.1.dist-info/entry_points.txt
whenami-0.2.1.dist-info/licenses/LICENSE
whenami-0.2.1.dist-info/RECORD
