Metadata-Version: 2.4
Name: whenami
Version: 0.2.1
Summary: A powerful Google Calendar tool that merges multiple calendars to find your true availability across work and personal schedules
Project-URL: Homepage, https://github.com/zampierilucas/whenami
Project-URL: Repository, https://github.com/zampierilucas/whenami
Project-URL: Issues, https://github.com/zampierilucas/whenami/issues
Project-URL: Changelog, https://github.com/zampierilucas/whenami/releases
Author-email: Lucas Zampieri <lcasmz54@gmail.com>
License:                                  Apache License
License-File: LICENSE
Keywords: calendar,google-calendar,productivity,scheduling,time-management
Classifier: Development Status :: 4 - Beta
Classifier: Environment :: Console
Classifier: Intended Audience :: Developers
Classifier: Intended Audience :: End Users/Desktop
Classifier: License :: OSI Approved :: Apache Software License
Classifier: Operating System :: OS Independent
Classifier: Programming Language :: Python :: 3
Classifier: Programming Language :: Python :: 3.9
Classifier: Programming Language :: Python :: 3.10
Classifier: Programming Language :: Python :: 3.11
Classifier: Programming Language :: Python :: 3.12
Classifier: Topic :: Office/Business :: Scheduling
Classifier: Topic :: Utilities
Requires-Python: >=3.9
Requires-Dist: google-api-python-client
Requires-Dist: google-auth
Requires-Dist: google-auth-oauthlib
Requires-Dist: litellm
Provides-Extra: dev
Requires-Dist: pytest; extra == 'dev'
Requires-Dist: pytest-cov; extra == 'dev'
